django_linkedin_middleware/__init__.py
django_linkedin_middleware/middleware.py
django_linkedin_middleware/settings.py
django_linkedin_middleware/tests/__init__.py
django_linkedin_middleware/tests/settings.py
django_linkedin_middleware/tests/test_middleware.py
django_linkedin_middleware-0.1.2.dist-info/LICENSE
django_linkedin_middleware-0.1.2.dist-info/METADATA
django_linkedin_middleware-0.1.2.dist-info/WHEEL
django_linkedin_middleware-0.1.2.dist-info/top_level.txt
django_linkedin_middleware-0.1.2.dist-info/RECORD
