Metadata-Version: 2.1
Name: django-linkedin-middleware
Version: 0.1.2
Summary: Django Middleware for LinkedIn API
Home-page: https://github.com/Squalex/LinkedinMiddleware
Author: Larry Mota--Lavigne
Author-email: larry.motalavigne@gmail.com
License: Apache License
Platform: UNKNOWN
Requires-Dist: django
Requires-Dist: linkedin
Requires-Dist: mock
Requires-Dist: python3-linkedin
